{
   "type": "recipe",
   "work_units": 1,
   "recipe_name": "i18n(additional_biomes:jobs.cook.recipes.cow_feed_recipe.recipe_name)",
   "description": "i18n(additional_biomes:jobs.cook.recipes.cow_feed_recipe.description)",
   "flavor": "i18n(additional_biomes:jobs.cook.recipes.cow_feed_recipe.flavor)",
   "portrait": "/additional_biomes/entities/food/cow_feed/cow_feed/cow_feed.png",
   "workshop": "stonehearth:cook:mill",
   "level_requirement": 1,
   "ingredients": [
      {
         "uri": "additional_biomes:resources:herb:tall_grass",
         "count": 2
      }
   ],
   "produces": [
      {
         "item": "additional_biomes:food:cow_feed"
      }
   ]
}